yetu/__init__.py
yetu/person/__init__.py
yetu/person/classes/__init__.py
yetu/person/classes/person.py
yetu/person/decorators/__init__.py
yetu/person/decorators/debugger.py
yetu/person/descriptors/__init__.py
yetu/person/descriptors/person.py
yetu/person/descriptors/residence.py
yetu/person/descriptors/social_network.py
yetu/person/metas/__init__.py
yetu/person/metas/person.py
yetu-1.2.dist-info/METADATA
yetu-1.2.dist-info/WHEEL
yetu-1.2.dist-info/top_level.txt
yetu-1.2.dist-info/RECORD
