Metadata-Version: 2.1
Name: yetu
Version: 1.2
Summary: General purpose software development frame-work.
Home-page: https://johnnes-smarts.ch
Author: David Johnnes
Author-email: david.johnnes@gmail.com
License: License :: OSI Approved :: MIT License
Keywords: Type checking and input validation already integrated,attributes,methods,classes,decorators and metaclasses.
Platform: UNKNOWN
Classifier: Programming Language :: Python :: 3
Classifier: License :: OSI Approved :: MIT License
Classifier: Operating System :: OS Independent
